{
  "config": {
    "financing": {
      "purchase_price": 940000.0,
      "ltv": 0.75,
      "interest_rate": 0.018,
      "amortization_rate": 0.01333,
      "num_owners": 4,
      "loan_amount": 705000.0,
      "equity_total": 235000.0,
      "equity_per_owner": 58750.0,
      "acquisition_costs_total": 9869.999999999998,
      "acquisition_costs_per_owner": 2467.4999999999995,
      "total_initial_investment": 244870.0,
      "total_initial_investment_per_owner": 61217.5
    },
    "rental": {
      "owner_nights_per_person": 5,
      "num_owners": 4,
      "occupancy_rate": 0.65,
      "average_daily_rate": 200.0,
      "days_per_year": 365,
      "gross_rental_income": 48783.0,
      "rented_nights": 226.05,
      "seasons": [
        {
          "name": "Winter Peak (Ski Season)",
          "months": [
            12,
            1,
            2,
            3
          ],
          "occupancy_rate": 0.75,
          "average_daily_rate": 260.0,
          "nights_in_season": 113,
          "rented_nights": 84.75,
          "season_income": 22035.0
        },
        {
          "name": "Summer Peak (Hiking Season)",
          "months": [
            6,
            7,
            8,
            9
          ],
          "occupancy_rate": 0.72,
          "average_daily_rate": 210.0,
          "nights_in_season": 115,
          "rented_nights": 82.8,
          "season_income": 17388.0
        },
        {
          "name": "Off-Peak (Shoulder Seasons)",
          "months": [
            4,
            5,
            10,
            11
          ],
          "occupancy_rate": 0.5,
          "average_daily_rate": 160.0,
          "nights_in_season": 117,
          "rented_nights": 58.5,
          "season_income": 9360.0
        }
      ]
    },
    "expenses": {
      "property_management_fee_rate": 0.2,
      "cleaning_cost_per_stay": 100.0,
      "average_length_of_stay": 1.7,
      "tourist_tax_per_person_per_night": 3.0,
      "avg_guests_per_night": 2.0,
      "insurance_annual": 1410.0,
      "nubbing_costs_annual": 2000.0,
      "electricity_internet_annual": 1000.0,
      "maintenance_rate": 0.0025,
      "property_value": 940000.0
    }
  },
  "annual_results": {
    "purchase_price": 940000.0,
    "loan_amount": 705000.0,
    "equity_total": 235000.0,
    "equity_per_owner": 58750.0,
    "acquisition_costs_total": 9869.999999999998,
    "acquisition_costs_per_owner": 2467.4999999999995,
    "total_initial_investment": 244870.0,
    "total_initial_investment_per_owner": 61217.5,
    "total_owner_nights": 20,
    "rentable_nights": 345,
    "rented_nights": 226.05,
    "gross_rental_income": 48783.0,
    "ota_fees_total": 7317.45,
    "ota_fee_rate_effective": 0.15,
    "net_rental_income": 41465.55,
    "property_management_cost": 5633.698235294119,
    "cleaning_cost": 13297.05882352941,
    "tourist_tax": 1356.3000000000002,
    "insurance": 1410.0,
    "nubbing_costs": 2000.0,
    "electricity_internet": 1000.0,
    "maintenance_reserve": 2350.0,
    "total_operating_expenses": 27047.057058823528,
    "net_operating_income": 14418.492941176475,
    "interest_payment": 12689.999999999998,
    "amortization_payment": 9397.65,
    "debt_service": 22087.649999999998,
    "cash_flow_after_debt_service": -7669.157058823523,
    "cash_flow_per_owner": -1917.2892647058807,
    "taxable_income": 1728.492941176477,
    "tax_liability": 518.547882352943,
    "tax_savings_total": 3806.999999999999,
    "tax_savings_per_owner": 951.7499999999998,
    "after_tax_cash_flow_total": -3862.1570588235236,
    "after_tax_cash_flow_per_owner": -965.5392647058809,
    "cap_rate_pct": 1.5338822277847315,
    "cash_on_cash_return_pct": -3.1319300276977673,
    "debt_coverage_ratio": 0.6527852868538064,
    "operating_expense_ratio_pct": 65.22777838187007,
    "seasonal_breakdown": {
      "Winter Peak (Ski Season)": {
        "nights": 84.75,
        "income": 22035.0,
        "rate": 260.0,
        "occupancy": 0.75,
        "available_nights": 113
      },
      "Summer Peak (Hiking Season)": {
        "nights": 82.8,
        "income": 17388.0,
        "rate": 210.0,
        "occupancy": 0.72,
        "available_nights": 115
      },
      "Off-Peak (Shoulder Seasons)": {
        "nights": 58.5,
        "income": 9360.0,
        "rate": 160.0,
        "occupancy": 0.5,
        "available_nights": 117
      }
    }
  },
  "projection_15yr": [
    {
      "year": 2026,
      "year_number": 1,
      "inflation_factor": 1.0,
      "appreciation_factor": 1.0,
      "property_value": 940000.0,
      "rented_nights": 226.05,
      "gross_rental_income": 48783.0,
      "ota_fees_total": 7317.45,
      "net_rental_income": 41465.55,
      "total_operating_expenses": 27047.057058823528,
      "net_operating_income": 14418.492941176475,
      "interest_payment": 12689.999999999998,
      "amortization_payment": 9397.65,
      "debt_service": 22087.649999999998,
      "cash_flow_after_debt_service": -7669.157058823523,
      "cash_flow_per_owner": -1917.2892647058807,
      "cumulative_cash_flow_per_owner": -1917.2892647058807,
      "taxable_income": 1728.492941176477,
      "tax_liability": 518.547882352943,
      "tax_savings_total": 3806.999999999999,
      "tax_savings_per_owner": 951.7499999999998,
      "after_tax_cash_flow_total": -3862.1570588235236,
      "after_tax_cash_flow_per_owner": -965.5392647058809,
      "remaining_loan_balance": 695602.35,
      "debt_coverage_ratio": 0.6527852868538064,
      "cap_rate_pct": 1.5338822277847315
    },
    {
      "year": 2027,
      "year_number": 2,
      "inflation_factor": 1.008,
      "appreciation_factor": 1.04,
      "property_value": 977600.0,
      "rented_nights": 227.85840000000002,
      "gross_rental_income": 49173.264,
      "ota_fees_total": 7375.9896,
      "net_rental_income": 41797.2744,
      "total_operating_expenses": 27338.633515294117,
      "net_operating_income": 14458.640884705885,
      "interest_payment": 12520.842299999998,
      "amortization_payment": 9397.65,
      "debt_service": 21918.492299999998,
      "cash_flow_after_debt_service": -7459.851415294113,
      "cash_flow_per_owner": -1864.9628538235283,
      "cumulative_cash_flow_per_owner": -3782.252118529409,
      "taxable_income": 1937.7985847058862,
      "tax_liability": 581.3395754117658,
      "tax_savings_total": 3756.2526899999993,
      "tax_savings_per_owner": 939.0631724999998,
      "after_tax_cash_flow_total": -3703.598725294114,
      "after_tax_cash_flow_per_owner": -925.8996813235285,
      "remaining_loan_balance": 686204.7,
      "debt_coverage_ratio": 0.6596549017518821,
      "cap_rate_pct": 1.4789935438528932
    },
    {
      "year": 2028,
      "year_number": 3,
      "inflation_factor": 1.016064,
      "appreciation_factor": 1.0816000000000001,
      "property_value": 1016704.0000000001,
      "rented_nights": 229.68126720000004,
      "gross_rental_income": 49566.650112,
      "ota_fees_total": 7434.9975168,
      "net_rental_income": 42131.6525952,
      "total_operating_expenses": 27635.550583416472,
      "net_operating_income": 14496.102011783529,
      "interest_payment": 12351.684599999999,
      "amortization_payment": 9397.65,
      "debt_service": 21749.3346,
      "cash_flow_after_debt_service": -7253.23258821647,
      "cash_flow_per_owner": -1813.3081470541174,
      "cumulative_cash_flow_per_owner": -5595.560265583526,
      "taxable_income": 2144.41741178353,
      "tax_liability": 643.325223535059,
      "tax_savings_total": 3705.5053799999996,
      "tax_savings_per_owner": 926.3763449999999,
      "after_tax_cash_flow_total": -3547.72720821647,
      "after_tax_cash_flow_per_owner": -886.9318020541175,
      "remaining_loan_balance": 676807.0499999999,
      "debt_coverage_ratio": 0.6665078393609122,
      "cap_rate_pct": 1.4257937425035732
    },
    {
      "year": 2029,
      "year_number": 4,
      "inflation_factor": 1.024192512,
      "appreciation_factor": 1.124864,
      "property_value": 1057372.1600000001,
      "rented_nights": 231.5187173376,
      "gross_rental_income": 49963.183312896,
      "ota_fees_total": 7494.4774969344,
      "net_rental_income": 42468.7058159616,
      "total_operating_expenses": 27937.9713080838,
      "net_operating_income": 14530.734507877798,
      "interest_payment": 12182.526899999997,
      "amortization_payment": 9397.65,
      "debt_service": 21580.1769,
      "cash_flow_after_debt_service": -7049.4423921222005,
      "cash_flow_per_owner": -1762.3605980305501,
      "cumulative_cash_flow_per_owner": -7357.920863614077,
      "taxable_income": 2348.207607877801,
      "tax_liability": 704.4622823633403,
      "tax_savings_total": 3654.758069999999,
      "tax_savings_per_owner": 913.6895174999997,
      "after_tax_cash_flow_total": -3394.6843221222016,
      "after_tax_cash_flow_per_owner": -848.6710805305504,
      "remaining_loan_balance": 667409.3999999999,
      "debt_coverage_ratio": 0.6733371359841726,
      "cap_rate_pct": 1.3742308581188478
    },
    {
      "year": 2030,
      "year_number": 5,
      "inflation_factor": 1.032386052096,
      "appreciation_factor": 1.1698585600000002,
      "property_value": 1099667.0464,
      "rented_nights": 233.3708670763008,
      "gross_rental_income": 50362.88877939917,
      "ota_fees_total": 7554.4333169098745,
      "net_rental_income": 42808.45546248929,
      "total_operating_expenses": 28246.06485134847,
      "net_operating_income": 14562.390611140821,
      "interest_payment": 12013.369199999997,
      "amortization_payment": 9397.65,
      "debt_service": 21411.019199999995,
      "cash_flow_after_debt_service": -6848.628588859174,
      "cash_flow_per_owner": -1712.1571472147934,
      "cumulative_cash_flow_per_owner": -9070.07801082887,
      "taxable_income": 2549.021411140824,
      "tax_liability": 764.7064233422471,
      "tax_savings_total": 3604.010759999999,
      "tax_savings_per_owner": 901.0026899999998,
      "after_tax_cash_flow_total": -3244.6178288591746,
      "after_tax_cash_flow_per_owner": -811.1544572147936,
      "remaining_loan_balance": 658011.7499999999,
      "debt_coverage_ratio": 0.6801353300893226,
      "cap_rate_pct": 1.3242545240228834
    },
    {
      "year": 2031,
      "year_number": 6,
      "inflation_factor": 1.0406451405127681,
      "appreciation_factor": 1.2166529024000001,
      "property_value": 1143653.7282560002,
      "rented_nights": 235.23783401291124,
      "gross_rental_income": 50765.79188963437,
      "ota_fees_total": 7614.868783445155,
      "net_rental_income": 43150.92310618921,
      "total_operating_expenses": 28560.006733871265,
      "net_operating_income": 14590.916372317948,
      "interest_payment": 11844.211499999998,
      "amortization_payment": 9397.65,
      "debt_service": 21241.8615,
      "cash_flow_after_debt_service": -6650.945127682051,
      "cash_flow_per_owner": -1662.7362819205127,
      "cumulative_cash_flow_per_owner": -10732.814292749383,
      "taxable_income": 2746.7048723179505,
      "tax_liability": 824.0114616953852,
      "tax_savings_total": 3553.263449999999,
      "tax_savings_per_owner": 888.3158624999998,
      "after_tax_cash_flow_total": -3097.681677682052,
      "after_tax_cash_flow_per_owner": -774.420419420513,
      "remaining_loan_balance": 648614.0999999999,
      "debt_coverage_ratio": 0.6868944311833475,
      "cap_rate_pct": 1.2758159232837176
    },
    {
      "year": 2032,
      "year_number": 7,
      "inflation_factor": 1.04897030163687,
      "appreciation_factor": 1.2653190184960004,
      "property_value": 1189399.8773862403,
      "rented_nights": 237.1197366850145,
      "gross_rental_income": 51171.91822475143,
      "ota_fees_total": 7675.787733712715,
      "net_rental_income": 43496.13049103872,
      "total_operating_expenses": 28879.979086002706,
      "net_operating_income": 14616.151405036013,
      "interest_payment": 11675.053799999996,
      "amortization_payment": 9397.65,
      "debt_service": 21072.703799999996,
      "cash_flow_after_debt_service": -6456.552394963983,
      "cash_flow_per_owner": -1614.1380987409957,
      "cumulative_cash_flow_per_owner": -12346.952391490378,
      "taxable_income": 2941.097605036017,
      "tax_liability": 882.329281510805,
      "tax_savings_total": 3502.516139999999,
      "tax_savings_per_owner": 875.6290349999997,
      "after_tax_cash_flow_total": -2954.036254963984,
      "after_tax_cash_flow_per_owner": -738.509063740996,
      "remaining_loan_balance": 639216.4499999998,
      "debt_coverage_ratio": 0.6936058867318211,
      "cap_rate_pct": 1.228867741028834
    },
    {
      "year": 2033,
      "year_number": 8,
      "inflation_factor": 1.0573620640499652,
      "appreciation_factor": 1.3159317792358403,
      "property_value": 1236975.8724816898,
      "rented_nights": 239.01669457849465,
      "gross_rental_income": 51581.29357054945,
      "ota_fees_total": 7737.194035582417,
      "net_rental_income": 43844.099534967034,
      "total_operating_expenses": 29206.17090888163,
      "net_operating_income": 14637.928626085402,
      "interest_payment": 11505.896099999996,
      "amortization_payment": 9397.65,
      "debt_service": 20903.546099999996,
      "cash_flow_after_debt_service": -6265.617473914594,
      "cash_flow_per_owner": -1566.4043684786484,
      "cumulative_cash_flow_per_owner": -13913.356759969027,
      "taxable_income": 3132.032526085406,
      "tax_liability": 939.6097578256217,
      "tax_savings_total": 3451.7688299999986,
      "tax_savings_per_owner": 862.9422074999997,
      "after_tax_cash_flow_total": -2813.848643914595,
      "after_tax_cash_flow_per_owner": -703.4621609786487,
      "remaining_loan_balance": 629818.7999999998,
      "debt_coverage_ratio": 0.7002605469932877,
      "cap_rate_pct": 1.183364118227947
    },
    {
      "year": 2034,
      "year_number": 9,
      "inflation_factor": 1.065820960562365,
      "appreciation_factor": 1.3685690504052739,
      "property_value": 1286454.9073809574,
      "rented_nights": 240.92882813512261,
      "gross_rental_income": 51993.94391911385,
      "ota_fees_total": 7799.091587867078,
      "net_rental_income": 44194.85233124677,
      "total_operating_expenses": 29538.77834595122,
      "net_operating_income": 14656.073985295552,
      "interest_payment": 11336.738399999997,
      "amortization_payment": 9397.65,
      "debt_service": 20734.388399999996,
      "cash_flow_after_debt_service": -6078.314414704444,
      "cash_flow_per_owner": -1519.578603676111,
      "cumulative_cash_flow_per_owner": -15432.935363645138,
      "taxable_income": 3319.3355852955556,
      "tax_liability": 995.8006755886666,
      "tax_savings_total": 3401.021519999999,
      "tax_savings_per_owner": 850.2553799999997,
      "after_tax_cash_flow_total": -2677.292894704445,
      "after_tax_cash_flow_per_owner": -669.3232236761113,
      "remaining_loan_balance": 620421.1499999998,
      "debt_coverage_ratio": 0.7068486276303937,
      "cap_rate_pct": 1.1392606068978564
    },
    {
      "year": 2035,
      "year_number": 10,
      "inflation_factor": 1.0743475282468637,
      "appreciation_factor": 1.423311812421485,
      "property_value": 1337913.103676196,
      "rented_nights": 242.85625876020356,
      "gross_rental_income": 52409.895470466756,
      "ota_fees_total": 7861.484320570013,
      "net_rental_income": 44548.41114989674,
      "total_operating_expenses": 29878.00496530931,
      "net_operating_income": 14670.406184587431,
      "interest_payment": 11167.580699999995,
      "amortization_payment": 9397.65,
      "debt_service": 20565.230699999993,
      "cash_flow_after_debt_service": -5894.824515412562,
      "cash_flow_per_owner": -1473.7061288531404,
      "cumulative_cash_flow_per_owner": -16906.64149249828,
      "taxable_income": 3502.825484587436,
      "tax_liability": 1050.8476453762307,
      "tax_savings_total": 3350.274209999998,
      "tax_savings_per_owner": 837.5685524999996,
      "after_tax_cash_flow_total": -2544.5503054125634,
      "after_tax_cash_flow_per_owner": -636.1375763531408,
      "remaining_loan_balance": 611023.4999999998,
      "debt_coverage_ratio": 0.7133596699495054,
      "cap_rate_pct": 1.096514126685614
    },
    {
      "year": 2036,
      "year_number": 11,
      "inflation_factor": 1.0829423084728387,
      "appreciation_factor": 1.4802442849183444,
      "property_value": 1391429.6278232436,
      "rented_nights": 244.7991088302852,
      "gross_rental_income": 52829.17463423049,
      "ota_fees_total": 7924.376195134573,
      "net_rental_income": 44904.79843909592,
      "total_operating_expenses": 30224.06205332588,
      "net_operating_income": 14680.736385770037,
      "interest_payment": 10998.422999999995,
      "amortization_payment": 9397.65,
      "debt_service": 20396.072999999997,
      "cash_flow_after_debt_service": -5715.33661422996,
      "cash_flow_per_owner": -1428.83415355749,
      "cumulative_cash_flow_per_owner": -18335.47564605577,
      "taxable_income": 3682.3133857700414,
      "tax_liability": 1104.6940157310123,
      "tax_savings_total": 3299.5268999999985,
      "tax_savings_per_owner": 824.8817249999996,
      "after_tax_cash_flow_total": -2415.8097142299616,
      "after_tax_cash_flow_per_owner": -603.9524285574904,
      "remaining_loan_balance": 601625.8499999997,
      "debt_coverage_ratio": 0.7197824986099058,
      "cap_rate_pct": 1.0550829227875953
    },
    {
      "year": 2037,
      "year_number": 12,
      "inflation_factor": 1.0916058469406213,
      "appreciation_factor": 1.5394540563150783,
      "property_value": 1447086.8129361735,
      "rented_nights": 246.75750170092746,
      "gross_rental_income": 53251.80803130433,
      "ota_fees_total": 7987.771204695649,
      "net_rental_income": 45264.03682660868,
      "total_operating_expenses": 30577.168919978343,
      "net_operating_income": 14686.867906630338,
      "interest_payment": 10829.265299999995,
      "amortization_payment": 9397.65,
      "debt_service": 20226.915299999993,
      "cash_flow_after_debt_service": -5540.047393369656,
      "cash_flow_per_owner": -1385.011848342414,
      "cumulative_cash_flow_per_owner": -19720.487494398185,
      "taxable_income": 3857.602606630342,
      "tax_liability": 1157.2807819891025,
      "tax_savings_total": 3248.7795899999987,
      "tax_savings_per_owner": 812.1948974999997,
      "after_tax_cash_flow_total": -2291.267803369657,
      "after_tax_cash_flow_per_owner": -572.8169508424143,
      "remaining_loan_balance": 592228.1999999997,
      "debt_coverage_ratio": 0.7261051766321651,
      "cap_rate_pct": 1.0149265251633615
    },
    {
      "year": 2038,
      "year_number": 13,
      "inflation_factor": 1.1003386937161463,
      "appreciation_factor": 1.6010322185676815,
      "property_value": 1504970.2854536206,
      "rented_nights": 248.7315617145349,
      "gross_rental_income": 53677.82249555477,
      "ota_fees_total": 8051.673374333215,
      "net_rental_income": 45626.149121221555,
      "total_operating_expenses": 30937.553216373064,
      "net_operating_income": 14688.595904848491,
      "interest_payment": 10660.107599999994,
      "amortization_payment": 9397.65,
      "debt_service": 20057.757599999994,
      "cash_flow_after_debt_service": -5369.1616951515025,
      "cash_flow_per_owner": -1342.2904237878756,
      "cumulative_cash_flow_per_owner": -21062.77791818606,
      "taxable_income": 4028.488304848497,
      "tax_liability": 1208.5464914545491,
      "tax_savings_total": 3198.032279999998,
      "tax_savings_per_owner": 799.5080699999995,
      "after_tax_cash_flow_total": -2171.1294151515044,
      "after_tax_cash_flow_per_owner": -542.7823537878761,
      "remaining_loan_balance": 582830.5499999997,
      "debt_coverage_ratio": 0.7323149575228936,
      "cap_rate_pct": 0.9760057090044889
    },
    {
      "year": 2039,
      "year_number": 14,
      "inflation_factor": 1.1091414032658755,
      "appreciation_factor": 1.6650735073103888,
      "property_value": 1565169.0968717656,
      "rented_nights": 250.72141420825116,
      "gross_rental_income": 54107.245075519204,
      "ota_fees_total": 8116.086761327881,
      "net_rental_income": 45991.15831419132,
      "total_operating_expenses": 31305.451264940337,
      "net_operating_income": 14685.707049250985,
      "interest_payment": 10490.949899999994,
      "amortization_payment": 9397.65,
      "debt_service": 19888.599899999994,
      "cash_flow_after_debt_service": -5202.892850749009,
      "cash_flow_per_owner": -1300.7232126872523,
      "cumulative_cash_flow_per_owner": -22363.501130873312,
      "taxable_income": 4194.757149250991,
      "tax_liability": 1258.4271447752972,
      "tax_savings_total": 3147.2849699999983,
      "tax_savings_per_owner": 786.8212424999996,
      "after_tax_cash_flow_total": -2055.6078807490107,
      "after_tax_cash_flow_per_owner": -513.9019701872527,
      "remaining_loan_balance": 573432.8999999997,
      "debt_coverage_ratio": 0.7383982343197014,
      "cap_rate_pct": 0.938282456419735
    },
    {
      "year": 2040,
      "year_number": 15,
      "inflation_factor": 1.1180145344920027,
      "appreciation_factor": 1.7316764476028044,
      "property_value": 1627775.860746636,
      "rented_nights": 252.72718552191722,
      "gross_rental_income": 54540.10303612337,
      "ota_fees_total": 8181.015455418506,
      "net_rental_income": 46359.087580704865,
      "total_operating_expenses": 31681.10840280961,
      "net_operating_income": 14677.979177895257,
      "interest_payment": 10321.792199999993,
      "amortization_payment": 9397.65,
      "debt_service": 19719.44219999999,
      "cash_flow_after_debt_service": -5041.463022104734,
      "cash_flow_per_owner": -1260.3657555261834,
      "cumulative_cash_flow_per_owner": -23623.866886399497,
      "taxable_income": 4356.186977895264,
      "tax_liability": 1306.8560933685792,
      "tax_savings_total": 3096.5376599999977,
      "tax_savings_per_owner": 774.1344149999994,
      "after_tax_cash_flow_total": -1944.925362104736,
      "after_tax_cash_flow_per_owner": -486.231340526184,
      "remaining_loan_balance": 564035.2499999997,
      "debt_coverage_ratio": 0.7443404853457398,
      "cap_rate_pct": 0.9017199192991283
    }
  ],
  "irr_results": {
    "equity_irr_with_sale_pct": 7.849611244630067,
    "equity_irr_without_sale_pct": 0.0,
    "project_irr_with_sale_pct": 4.436156087089326,
    "project_irr_without_sale_pct": -14.34708716673777,
    "sale_proceeds_per_owner": 234193.5234020997,
    "final_property_value": 1627775.860746636,
    "final_loan_balance": 564035.2499999997,
    "npv_at_5pct": 34644.14533360979,
    "moic": 3.439697088507375,
    "payback_period_years": 15,
    "gross_sale_price": 1627775.860746636,
    "selling_costs": 126966.51713823761,
    "net_sale_price": 1500809.3436083985,
    "selling_costs_rate_pct": 7.8
  },
  "kpis": {
    "cap_rate_pct": 1.5338822277847315,
    "cash_on_cash_return_pct": -3.1319300276977673,
    "debt_coverage_ratio": 0.6527852868538064,
    "operating_expense_ratio_pct": 65.22777838187007
  },
  "timestamp": "2026-01-28T08:03:07.393087"
}